Workbook
Name SegmentaciónDeDatos_Categoria: #N/A
Name SegmentaciónDeDatos_Mes: #N/A
Name SegmentaciónDeDatos_Region: #N/A

Sheet Dashboard Final
B2: Dashboard Ejecutivo — Cosmética Directa 2026
B3: =IF((SUMPRODUCT((MONTH(Datos_Base!$A$2:$A$396)>6)*Datos_Base!$I$2:$I$396)-SUMPRODUCT((MONTH(Datos_Base!$A$2:$A$396)<=6)*Datos_Base!$I$2:$I$396))/SUMPRODUCT((MONTH(Datos_Base!$A$2:$A$396)<=6)*Datos_Base!$I$2:$I$396)<0,"Las ventas muestran una desaceleración sostenida desde el tercer trimestre","Las ventas muestran una recuperación sostenida desde el tercer trimestre") -> Las ventas muestran una desaceleración sostenida desde el tercer trimestre
B6: VENTAS TOTALES 2026 | F6: % MARGEN | J6: CRECIMIENTO H2 vs H1
B7: =SUM(Datos_Base!I2:I396) -> 5923488.7 | F7: =SUM(Datos_Base!K2:K396)/SUM(Datos_Base!I2:I396) -> 0.48918407 | J7: =(SUMPRODUCT((MONTH(Datos_Base!$A$2:$A$396)>6)*Datos_Base!$I$2:$I$396)-SUMPRODUCT((MONTH(Datos_Base!$A$2:$A$396)<=6)*Datos_Base!$I$2:$I$396))/SUMPRODUCT((MONTH(Datos_Base!$A$2:$A$396)<=6)*Datos_Base!$I$2:$I$396) -> -0.23376507
B10: Facturación acumulada enero–diciembre | F10: Meta: 45% | J10: Segundo semestre vs. primer semestre
B13: Precio vs. Costo por transacción — detección de anomalías de pricing
B32: Notas de Análisis
B33: 1. La facturación cae 23,4% en el segundo semestre respecto al primero, con el punto más bajo en agosto — no es una caída puntual de un mes, es una tendencia sostenida de 4-5 meses.
B35: 2. El margen global (48,9%) está por encima de la meta del 45%, así que la caída de ventas no viene acompañada (todavía) de un problema de rentabilidad por unidad vendida.
B37: 3. En el gráfico de Precio vs. Costo no se ven outliers claros fuera del agrupamiento de cada categoría — la caída de facturación parece ser de volumen, no de una categoría con pricing roto.

Sheet Datos_Base
A1: Fecha | B1: Cliente | C1: Region | D1: Producto | E1: Categoria | F1: Unidades | G1: Precio_Unitario | H1: Costo_Unitario | I1: Monto_Venta | J1: Costo_Total | K1: Margen_Neto | L1: Precio_Maquillaje | M1: Costo_Maquillaje | N1: Precio_Perfumería | O1: Costo_Perfumería | P1: Precio_Cuidado Facial | Q1: Costo_Cuidado Facial | R1: Precio_Capilar | S1: Costo_Capilar | T1: Mes
A2: 46069 | B2: Consultora Elena | C2: Sur | D2: Fragancia Absolute Homme | E2: Perfumería | F2: 11 | G2: 3456.44 | H2: 1596.65 | I2: 38020.84 | J2: 17563.15 | K2: 20457.69 | L2: =IF($E2="Maquillaje",$G2,NA()) -> #N/A | M2: =IF($E2="Maquillaje",$H2,NA()) -> #N/A | N2: =IF($E2="Perfumería",$G2,NA()) -> 3456.44 | O2: =IF($E2="Perfumería",$H2,NA()) -> 1596.65 | P2: =IF($E2="Cuidado Facial",$G2,NA()) -> #N/A | Q2: =IF($E2="Cuidado Facial",$H2,NA()) -> #N/A | R2: =IF($E2="Capilar",$G2,NA()) -> #N/A | S2: =IF($E2="Capilar",$H2,NA()) -> #N/A | T2: =CHOOSE(MONTH(A2),"Enero","Febrero","Marzo","Abril","Mayo","Junio","Julio","Agosto","Septiembre","Octubre","Noviembre","Diciembre") -> Febrero
A3: 46308 | B3: Consultora Lucía | C3: Cuyo | D3: Base Fluida HD | E3: Maquillaje | F3: 5 | G3: 1467.47 | H3: 808.39 | I3: 7337.35 | J3: 4041.95 | K3: 3295.4 | L3: =IF($E3="Maquillaje",$G3,NA()) -> 1467.47 | M3: =IF($E3="Maquillaje",$H3,NA()) -> 808.39 | N3: =IF($E3="Perfumería",$G3,NA()) -> #N/A | O3: =IF($E3="Perfumería",$H3,NA()) -> #N/A | P3: =IF($E3="Cuidado Facial",$G3,NA()) -> #N/A | Q3: =IF($E3="Cuidado Facial",$H3,NA()) -> #N/A | R3: =IF($E3="Capilar",$G3,NA()) -> #N/A | S3: =IF($E3="Capilar",$H3,NA()) -> #N/A | T3: =CHOOSE(MONTH(A3),"Enero","Febrero","Marzo","Abril","Mayo","Junio","Julio","Agosto","Septiembre","Octubre","Noviembre","Diciembre") -> Octubre
A4: 46072 | B4: Consultora Elena | C4: Cuyo | D4: Fragancia Absolute Homme | E4: Perfumería | F4: 11 | G4: 3421.57 | H4: 1847.03 | I4: 37637.27 | J4: 20317.33 | K4: 17319.94 | L4: =IF($E4="Maquillaje",$G4,NA()) -> #N/A | M4: =IF($E4="Maquillaje",$H4,NA()) -> #N/A | N4: =IF($E4="Perfumería",$G4,NA()) -> 3421.57 | O4: =IF($E4="Perfumería",$H4,NA()) -> 1847.03 | P4: =IF($E4="Cuidado Facial",$G4,NA()) -> #N/A | Q4: =IF($E4="Cuidado Facial",$H4,NA()) -> #N/A | R4: =IF($E4="Capilar",$G4,NA()) -> #N/A | S4: =IF($E4="Capilar",$H4,NA()) -> #N/A | T4: =CHOOSE(MONTH(A4),"Enero","Febrero","Marzo","Abril","Mayo","Junio","Julio","Agosto","Septiembre","Octubre","Noviembre","Diciembre") -> Febrero
A5: 46150 | B5: Consultora Sofía | C5: Sur | D5: Sérum Ácido Hialurónico | E5: Cuidado Facial | F5: 8 | G5: 2257.56 | H5: 1098.18 | I5: 18060.48 | J5: 8785.44 | K5: 9275.04 | L5: =IF($E5="Maquillaje",$G5,NA()) -> #N/A | M5: =IF($E5="Maquillaje",$H5,NA()) -> #N/A | N5: =IF($E5="Perfumería",$G5,NA()) -> #N/A | O5: =IF($E5="Perfumería",$H5,NA()) -> #N/A | P5: =IF($E5="Cuidado Facial",$G5,NA()) -> 2257.56 | Q5: =IF($E5="Cuidado Facial",$H5,NA()) -> 1098.18 | R5: =IF($E5="Capilar",$G5,NA()) -> #N/A | S5: =IF($E5="Capilar",$H5,NA()) -> #N/A | T5: =CHOOSE(MONTH(A5),"Enero","Febrero","Marzo","Abril","Mayo","Junio","Julio","Agosto","Septiembre","Octubre","Noviembre","Diciembre") -> Mayo
A6: 46237 | B6: Venta Web Directa | C6: Cuyo | D6: Shampoo Nutrición | E6: Capilar | F6: 11 | G6: 869.75 | H6: 485.58 | I6: 9567.25 | J6: 5341.38 | K6: 4225.87 | L6: =IF($E6="Maquillaje",$G6,NA()) -> #N/A | M6: =IF($E6="Maquillaje",$H6,NA()) -> #N/A | N6: =IF($E6="Perfumería",$G6,NA()) -> #N/A | O6: =IF($E6="Perfumería",$H6,NA()) -> #N/A | P6: =IF($E6="Cuidado Facial",$G6,NA()) -> #N/A | Q6: =IF($E6="Cuidado Facial",$H6,NA()) -> #N/A | R6: =IF($E6="Capilar",$G6,NA()) -> 869.75 | S6: =IF($E6="Capilar",$H6,NA()) -> 485.58 | T6: =CHOOSE(MONTH(A6),"Enero","Febrero","Marzo","Abril","Mayo","Junio","Julio","Agosto","Septiembre","Octubre","Noviembre","Diciembre") -> Agosto
A7: 46202 | B7: Consultora Sofía | C7: Sur | D7: Base Fluida HD | E7: Maquillaje | F7: 8 | G7: 1507.14 | H7: 712.14 | I7: 12057.12 | J7: 5697.12 | K7: 6360 | L7: =IF($E7="Maquillaje",$G7,NA()) -> 1507.14 | M7: =IF($E7="Maquillaje",$H7,NA()) -> 712.14 | N7: =IF($E7="Perfumería",$G7,NA()) -> #N/A | O7: =IF($E7="Perfumería",$H7,NA()) -> #N/A | P7: =IF($E7="Cuidado Facial",$G7,NA()) -> #N/A | Q7: =IF($E7="Cuidado Facial",$H7,NA()) -> #N/A | R7: =IF($E7="Capilar",$G7,NA()) -> #N/A | S7: =IF($E7="Capilar",$H7,NA()) -> #N/A | T7: =CHOOSE(MONTH(A7),"Enero","Febrero","Marzo","Abril","Mayo","Junio","Julio","Agosto","Septiembre","Octubre","Noviembre","Diciembre") -> Junio
A8: 46371 | B8: Venta Web Directa | C8: Cuyo | D8: Labial Matte Long | E8: Maquillaje | F8: 6 | G8: 1120.33 | H8: 600.22 | I8: 6721.98 | J8: 3601.32 | K8: 3120.66 | L8: =IF($E8="Maquillaje",$G8,NA()) -> 1120.33 | M8: =IF($E8="Maquillaje",$H8,NA()) -> 600.22 | N8: =IF($E8="Perfumería",$G8,NA()) -> #N/A | O8: =IF($E8="Perfumería",$H8,NA()) -> #N/A | P8: =IF($E8="Cuidado Facial",$G8,NA()) -> #N/A | Q8: =IF($E8="Cuidado Facial",$H8,NA()) -> #N/A | R8: =IF($E8="Capilar",$G8,NA()) -> #N/A | S8: =IF($E8="Capilar",$H8,NA()) -> #N/A | T8: =CHOOSE(MONTH(A8),"Enero","Febrero","Marzo","Abril","Mayo","Junio","Julio","Agosto","Septiembre","Octubre","Noviembre","Diciembre") -> Diciembre
A9: 46149 | B9: Consultora Lucía | C9: Cuyo | D9: Máscara Reconstructora | E9: Capilar | F9: 9 | G9: 1051.12 | H9: 519.34 | I9: 9460.08 | J9: 4674.06 | K9: 4786.02 | L9: =IF($E9="Maquillaje",$G9,NA()) -> #N/A | M9: =IF($E9="Maquillaje",$H9,NA()) -> #N/A | N9: =IF($E9="Perfumería",$G9,NA()) -> #N/A | O9: =IF($E9="Perfumería",$H9,NA()) -> #N/A | P9: =IF($E9="Cuidado Facial",$G9,NA()) -> #N/A | Q9: =IF($E9="Cuidado Facial",$H9,NA()) -> #N/A | R9: =IF($E9="Capilar",$G9,NA()) -> 1051.12 | S9: =IF($E9="Capilar",$H9,NA()) -> 519.34 | T9: =CHOOSE(MONTH(A9),"Enero","Febrero","Marzo","Abril","Mayo","Junio","Julio","Agosto","Septiembre","Octubre","Noviembre","Diciembre") -> Mayo
A10: 46206 | B10: Consultora Lucía | C10: Cuyo | D10: Base Fluida HD | E10: Maquillaje | F10: 3 | G10: 1372.27 | H10: 738.4 | I10: 4116.81 | J10: 2215.2 | K10: 1901.61 | L10: =IF($E10="Maquillaje",$G10,NA()) -> 1372.27 | M10: =IF($E10="Maquillaje",$H10,NA()) -> 738.4 | N10: =IF($E10="Perfumería",$G10,NA()) -> #N/A | O10: =IF($E10="Perfumería",$H10,NA()) -> #N/A | P10: =IF($E10="Cuidado Facial",$G10,NA()) -> #N/A | Q10: =IF($E10="Cuidado Facial",$H10,NA()) -> #N/A | R10: =IF($E10="Capilar",$G10,NA()) -> #N/A | S10: =IF($E10="Capilar",$H10,NA()) -> #N/A | T10: =CHOOSE(MONTH(A10),"Enero","Febrero","Marzo","Abril","Mayo","Junio","Julio","Agosto","Septiembre","Octubre","Noviembre","Diciembre") -> Julio
A11: 46025 | B11: Consultora Laura | C11: Sur | D11: Perfume Colonia Femme | E11: Perfumería | F11: 14 | G11: 3209.91 | H11: 1637.63 | I11: 44938.74 | J11: 22926.82 | K11: 22011.92 | L11: =IF($E11="Maquillaje",$G11,NA()) -> #N/A | M11: =IF($E11="Maquillaje",$H11,NA()) -> #N/A | N11: =IF($E11="Perfumería",$G11,NA()) -> 3209.91 | O11: =IF($E11="Perfumería",$H11,NA()) -> 1637.63 | P11: =IF($E11="Cuidado Facial",$G11,NA()) -> #N/A | Q11: =IF($E11="Cuidado Facial",$H11,NA()) -> #N/A | R11: =IF($E11="Capilar",$G11,NA()) -> #N/A | S11: =IF($E11="Capilar",$H11,NA()) -> #N/A | T11: =CHOOSE(MONTH(A11),"Enero","Febrero","Marzo","Abril","Mayo","Junio","Julio","Agosto","Septiembre","Octubre","Noviembre","Diciembre") -> Enero
A12: 46371 | B12: Venta Web Directa | C12: Cuyo | D12: Shampoo Nutrición | E12: Capilar | F12: 8 | G12: 975.52 | H12: 437.98 | I12: 7804.16 | J12: 3503.84 | K12: 4300.32 | L12: =IF($E12="Maquillaje",$G12,NA()) -> #N/A | M12: =IF($E12="Maquillaje",$H12,NA()) -> #N/A | N12: =IF($E12="Perfumería",$G12,NA()) -> #N/A | O12: =IF($E12="Perfumería",$H12,NA()) -> #N/A | P12: =IF($E12="Cuidado Facial",$G12,NA()) -> #N/A | Q12: =IF($E12="Cuidado Facial",$H12,NA()) -> #N/A | R12: =IF($E12="Capilar",$G12,NA()) -> 975.52 | S12: =IF($E12="Capilar",$H12,NA()) -> 437.98 | T12: =CHOOSE(MONTH(A12),"Enero","Febrero","Marzo","Abril","Mayo","Junio","Julio","Agosto","Septiembre","Octubre","Noviembre","Diciembre") -> Diciembre
A13: 46197 | B13: Consultora Elena | C13: Norte | D13: Base Fluida HD | E13: Maquillaje | F13: 10 | G13: 1312.4 | H13: 838.4 | I13: 13124 | J13: 8384 | K13: 4740 | L13: =IF($E13="Maquillaje",$G13,NA()) -> 1312.4 | M13: =IF($E13="Maquillaje",$H13,NA()) -> 838.4 | N13: =IF($E13="Perfumería",$G13,NA()) -> #N/A | O13: =IF($E13="Perfumería",$H13,NA()) -> #N/A | P13: =IF($E13="Cuidado Facial",$G13,NA()) -> #N/A | Q13: =IF($E13="Cuidado Facial",$H13,NA()) -> #N/A | R13: =IF($E13="Capilar",$G13,NA()) -> #N/A | S13: =IF($E13="Capilar",$H13,NA()) -> #N/A | T13: =CHOOSE(MONTH(A13),"Enero","Febrero","Marzo","Abril","Mayo","Junio","Julio","Agosto","Septiembre","Octubre","Noviembre","Diciembre") -> Junio
... A396: 46060 | B396: Consultora Lucía | C396: Cuyo | D396: Perfume Colonia Femme | E396: Perfumería | F396: 7 | G396: 3087.55 | H396: 1731.17 | I396: 21612.85 | J396: 12118.19 | K396: 9494.66 | L396: =IF($E396="Maquillaje",$G396,NA()) -> #N/A | M396: =IF($E396="Maquillaje",$H396,NA()) -> #N/A | N396: =IF($E396="Perfumería",$G396,NA()) -> 3087.55 | O396: =IF($E396="Perfumería",$H396,NA()) -> 1731.17 | P396: =IF($E396="Cuidado Facial",$G396,NA()) -> #N/A | Q396: =IF($E396="Cuidado Facial",$H396,NA()) -> #N/A | R396: =IF($E396="Capilar",$G396,NA()) -> #N/A | S396: =IF($E396="Capilar",$H396,NA()) -> #N/A | T396: =CHOOSE(MONTH(A396),"Enero","Febrero","Marzo","Abril","Mayo","Junio","Julio","Agosto","Septiembre","Octubre","Noviembre","Diciembre") -> Febrero

Sheet Estadística_Descriptiva
B2: Estadística Descriptiva — Monto de Venta
B3: Variable analizada: Monto_Venta (columna I de Datos_Base). Podés confirmar estos valores corriendo Datos > Análisis de datos > Estadística descriptiva sobre el mismo rango.
B5: Media | C5: =AVERAGE(Datos_Base!I2:I396) -> 14996.174
B6: Error típico | C6: =STDEV(Datos_Base!I2:I396)/SQRT(COUNT(Datos_Base!I2:I396)) -> 580.74211
B7: Mediana | C7: =MEDIAN(Datos_Base!I2:I396) -> 11947
B8: Moda | C8: =IFERROR(MODE(Datos_Base!I2:I396),"Sin moda (valores continuos, sin repetidos)") -> Sin moda (valores continuos, sin repetidos)
B9: Desviación estándar | C9: =STDEV(Datos_Base!I2:I396) -> 11542.021
B10: Varianza de la muestra | C10: =VAR(Datos_Base!I2:I396) -> 1.3321825e+08
B11: Curtosis | C11: =KURT(Datos_Base!I2:I396) -> 1.3054902
B12: Coeficiente de asimetría | C12: =SKEW(Datos_Base!I2:I396) -> 1.2820243
B13: Rango | C13: =MAX(Datos_Base!I2:I396)-MIN(Datos_Base!I2:I396) -> 53532
B14: Mínimo | C14: =MIN(Datos_Base!I2:I396) -> 857.4
B15: Máximo | C15: =MAX(Datos_Base!I2:I396) -> 54389.4
B16: Suma | C16: =SUM(Datos_Base!I2:I396) -> 5923488.7
B17: Cuenta | C17: =COUNT(Datos_Base!I2:I396) -> 395

Sheet Escenarios_Resumen
B2: Resumen de Escenarios — Sensibilidad del Margen Neto al Costo
B3: Variable variada: Costo_Unitario (±10%). Podés replicar esto con el Administrador de Escenarios (Datos > Análisis de hipótesis > Administrador de escenarios) usando estos mismos 3 valores.
B5: Supuesto | C5: Pesimista | D5: Base | E5: Optimista
B6: Variación de Costo_Unitario | C6: 0.1 | D6: 0 | E6: -0.1
B7: Monto Venta Total | C7: =SUM(Datos_Base!$I$2:$I$396) -> 5923488.7 | D7: =SUM(Datos_Base!$I$2:$I$396) -> 5923488.7 | E7: =SUM(Datos_Base!$I$2:$I$396) -> 5923488.7
B8: Costo Total ajustado | C8: =SUM(Datos_Base!$J$2:$J$396)*(1+C6) -> 3328393.6 | D8: =SUM(Datos_Base!$J$2:$J$396)*(1+D6) -> 3025812.4 | E8: =SUM(Datos_Base!$J$2:$J$396)*(1+E6) -> 2723231.2
B9: Margen Neto Total | C9: =C7-C8 -> 2595095.1 | D9: =D7-D8 -> 2897676.3 | E9: =E7-E8 -> 3200257.5
B10: Margen % | C10: =C9/C7 -> 0.43810248 | D10: =D9/D7 -> 0.48918407 | E10: =E9/E7 -> 0.54026566
